{"is_source_file": false, "format": "", "description": "", "external_files": [], "external_methods": [], "published": [], "classes": [], "methods": [], "calls": [], "search-terms": [], "state": 2, "file_id": 17, "knowledge_revision": 36, "git_revision": "90161cabf38c326a1892f2fee394b3e5c78106d1", "hash": "1077e968c0082d396b98a32cfb5be9f2", "format-version": 4, "code-base-name": "notes_frontend", "filename": "notes_frontend/src/global.css", "revision_history": [{"36": "90161cabf38c326a1892f2fee394b3e5c78106d1"}]}